CHANGES
COPYRIGHT
MANIFEST.in
NOTICE
README
TODO
setup.cfg
setup.py
TracBasicMacros.egg-info/PKG-INFO
TracBasicMacros.egg-info/SOURCES.txt
TracBasicMacros.egg-info/dependency_links.txt
TracBasicMacros.egg-info/entry_points.txt
TracBasicMacros.egg-info/requires.txt
TracBasicMacros.egg-info/top_level.txt
tracbm/__init__.py
tracbm/config.py
tracbm/util.py
tracbm/wiki.py