Metadata-Version: 1.1
Name: TracBasicMacros
Version: 1.0.1
Summary: Simple but useful Trac macros
Home-page: https://opensvn.csie.org/traccgi/swlcu/wiki/En/Devel/TracBasicMacros
Author: Olemis Lang
Author-email: olemis+trac@gmail.com
License: UNKNOWN
Download-URL: http://pypi.python.org/packages/2.5/T/TracBasicMacros/TracBasicMacros-1.0.1-py2.5.egg
Platform: UNKNOWN
Classifier: Development Status :: 3 - Alpha
Classifier: Environment :: Plugins
Classifier: Environment :: Web Environment
Classifier: Framework :: Trac
Classifier: Intended Audience :: Developers
Classifier: Intended Audience :: Information Technology
Classifier: Intended Audience :: Other Audience
Classifier: Intended Audience :: System Administrators
Classifier: License :: OSI Approved :: Apache Software License
Classifier: Operating System :: OS Independent
Classifier: Programming Language :: Python
Classifier: Programming Language :: Python :: 2.5
Classifier: Topic :: Internet :: WWW/HTTP :: Dynamic Content :: CGI Tools/Libraries
Classifier: Topic :: Internet :: WWW/HTTP :: HTTP Servers
Classifier: Topic :: Internet :: WWW/HTTP :: WSGI
Classifier: Topic :: Software Development :: Bug Tracking
Classifier: Topic :: Software Development :: Libraries :: Application Frameworks
Classifier: Topic :: Software Development :: Libraries :: Python Modules
Requires: trac
Requires: trac
Provides: tracbm (1.0.1)
Obsoletes: tracbm (>=1.0.0, <1.0.1)
